shaheenviz/__init__.py
shaheenviz/cli.py
shaheenviz/core.py
shaheenviz/profiling_wrapper.py
shaheenviz/rust_accelerated.py
shaheenviz/shaheenviz_rs.pyd
shaheenviz/sweetviz_wrapper.py
shaheenviz/utils.py
shaheenviz-0.1.3.dist-info/licenses/LICENSE
tests/__init__.py
tests/test_core.py
shaheenviz-0.1.3.dist-info/METADATA
shaheenviz-0.1.3.dist-info/WHEEL
shaheenviz-0.1.3.dist-info/entry_points.txt
shaheenviz-0.1.3.dist-info/top_level.txt
shaheenviz-0.1.3.dist-info/RECORD
