Metadata-Version: 2.4
Name: shaheenviz
Version: 0.1.3
Summary: Shaheenviz combines the analytical power of YData Profiling with the stunning visuals of Sweetviz to deliver a unified, automatic EDA solution.
Home-page: https://github.com/hamza-0987/shaheenviz
Author: Hamza
Author-email: Hamza <certification1290@gmail.com>
Maintainer-email: Hamza <certification1290@gmail.com>
License-Expression: MIT
Project-URL: Homepage, https://github.com/hamza-0987/shaheenviz
Project-URL: Documentation, https://github.com/hamza-0987/shaheenviz#readme
Project-URL: Repository, https://github.com/hamza-0987/shaheenviz
Project-URL: Bug Tracker, https://github.com/hamza-0987/shaheenviz/issues
Keywords: eda,data-analysis,data-visualization,ydata-profiling,sweetviz,pandas
Classifier: Development Status :: 3 - Alpha
Classifier: Intended Audience :: Developers
Classifier: Intended Audience :: Science/Research
Classifier: Operating System :: OS Independent
Classifier: Programming Language :: Python :: 3
Classifier: Programming Language :: Python :: 3.7
Classifier: Programming Language :: Python :: 3.8
Classifier: Programming Language :: Python :: 3.9
Classifier: Programming Language :: Python :: 3.10
Classifier: Programming Language :: Python :: 3.11
Classifier: Topic :: Scientific/Engineering :: Information Analysis
Classifier: Topic :: Software Development :: Libraries :: Python Modules
Requires-Python: >=3.7
License-File: LICENSE
Requires-Dist: pandas>=1.1.0
Requires-Dist: numpy>=1.18.0
Requires-Dist: matplotlib>=3.3.0
Requires-Dist: seaborn>=0.11.0
Requires-Dist: sweetviz>=2.1.4
Requires-Dist: ydata-profiling>=4.2.0
Requires-Dist: scikit-learn>=0.24.0
Requires-Dist: plotly>=5.0.0
Requires-Dist: tqdm>=4.60.0
Provides-Extra: dev
Requires-Dist: pytest>=6.0; extra == "dev"
Requires-Dist: pytest-cov>=2.0; extra == "dev"
Requires-Dist: black>=21.0; extra == "dev"
Requires-Dist: flake8>=3.8; extra == "dev"
Requires-Dist: mypy>=0.800; extra == "dev"
Provides-Extra: pdf
Requires-Dist: pdfkit>=1.0.0; extra == "pdf"
Dynamic: author
Dynamic: home-page
Dynamic: license-file
Dynamic: requires-python
